.dockerignore
.gitignore
CHANGELOG.md
DEVELOP.md
LICENSE.txt
Makefile
README.md
RELEASE.md
environment.yml
pyproject.toml
requirements-package.txt
requirements.txt
setup.cfg
setup.py
.github/workflows/test.yml
cannerflow_jupyter_contents.egg-info/PKG-INFO
cannerflow_jupyter_contents.egg-info/SOURCES.txt
cannerflow_jupyter_contents.egg-info/dependency_links.txt
cannerflow_jupyter_contents.egg-info/not-zip-safe
cannerflow_jupyter_contents.egg-info/requires.txt
cannerflow_jupyter_contents.egg-info/top_level.txt
s3contents/__init__.py
s3contents/_generated_version.py
s3contents/blob_fs.py
s3contents/blobmanager.py
s3contents/gcs_fs.py
s3contents/gcsmanager.py
s3contents/genericfs.py
s3contents/genericmanager.py
s3contents/ipycompat.py
s3contents/s3_fs.py
s3contents/s3manager.py
s3contents/tests/__init__.py
s3contents/tests/test_blobmanager.py
s3contents/tests/test_blobmanager_with_prefix.py
s3contents/tests/test_gcsmanager.py
s3contents/tests/test_gcsmanager_with_prefix.py
s3contents/tests/test_import.py
s3contents/tests/test_s3manager.py
s3contents/tests/test_s3manager_with_prefix.py
s3contents/tests/utils.py