Metadata-Version: 2.1
Name: cannerflow-jupyter-contents
Version: 1.0.0
Summary: Azure Contents Manager for Jupyter
Home-page: UNKNOWN
Maintainer: Leo
Maintainer-email: leo@canner.io
License: Apache License, Version 2.0
Keywords: jupyter,blob,azure,contents-manager
Platform: UNKNOWN
Classifier: License :: OSI Approved :: Apache Software License
Classifier: Programming Language :: Python :: 3.6
Classifier: Programming Language :: Python :: 3.7
Classifier: Programming Language :: Python :: 3.8
Requires-Python: >=3.6
Provides-Extra: test
Provides-Extra: dev
